README.rst
setup.cfg
setup.py
django_nuts/__init__.py
django_nuts/admin.py
django_nuts/apps.py
django_nuts/models.py
django_nuts/tests.py
django_nuts.egg-info/PKG-INFO
django_nuts.egg-info/SOURCES.txt
django_nuts.egg-info/dependency_links.txt
django_nuts.egg-info/requires.txt
django_nuts.egg-info/top_level.txt
django_nuts/loaders/__init__.py
django_nuts/loaders/cz_nuts.py
django_nuts/loaders/cz_nuts4_lau.py
django_nuts/loaders/sk_nuts.py
django_nuts/migrations/0001_initial.py
django_nuts/migrations/__init__.py